Metadata-Version: 2.1
Name: pyrogeram
Version: 2.0.106
Summary: Seratus Persen Clone Pyrofork
Home-page: https://t.me/pyrogram
Author: rizaldevs
Author-email: rizaldaitona@gmail.com
Classifier: Programming Language :: Python :: 3.10
Classifier: License :: OSI Approved :: MIT License
Classifier: Operating System :: OS Independent
Requires-Dist: pyaes (==1.6.1)
Requires-Dist: pysocks (==1.7.1)
Requires-Dist: pymediainfo-pyrofork (<7.0.0,>=6.0.1)
Requires-Dist: tgcrypto
